polartools/__init__.py
polartools/_larch.py
polartools/_pyrixs.py
polartools/_version.py
polartools/absorption.py
polartools/area_detector_handlers.py
polartools/diffraction.py
polartools/load_data.py
polartools/manage_database.py
polartools/pressure_calibration.py
polartools/process_images.py
polartools/tests/__init__.py
polartools/tests/conftest.py
polartools/tests/test_absorption.py
polartools/tests/test_area_detector_handlers.py
polartools/tests/test_load_data.py
polartools/tests/test_manage_database.py
polartools/tests/test_pressure_calibration.py
polartools/tests/test_process_images.py
polartools-0.5.4.dist-info/AUTHORS.rst
polartools-0.5.4.dist-info/LICENSE.txt
polartools-0.5.4.dist-info/METADATA
polartools-0.5.4.dist-info/WHEEL
polartools-0.5.4.dist-info/top_level.txt
polartools-0.5.4.dist-info/RECORD
