Metadata-Version: 2.1
Name: polartools
Version: 0.5.4
Summary: Python package to read and process data from the APS Polar beamline
Home-page: https://github.com/gfabbris/polartools
Author: Argonne National Laboratory
Author-email: gfabbris@anl.gov
License: BSD (3-clause)
Classifier: Development Status :: 2 - Pre-Alpha
Classifier: Natural Language :: English
Classifier: Programming Language :: Python :: 3
Requires-Python: >=3.6
License-File: LICENSE.txt
License-File: AUTHORS.rst
Requires-Dist: numpy
Requires-Dist: matplotlib
Requires-Dist: pandas
Requires-Dist: scipy
Requires-Dist: lmfit
Requires-Dist: spec2nexus
Requires-Dist: ipython
Requires-Dist: numpydoc
Requires-Dist: sphinx-copybutton
Requires-Dist: suitcase-csv
Requires-Dist: suitcase-json-metadata
Requires-Dist: databroker<=1.9
Requires-Dist: databroker-pack
Requires-Dist: pyresttable
Requires-Dist: area-detector-handlers
Requires-Dist: hdf5plugin
Requires-Dist: dask
Requires-Dist: xraydb
Requires-Dist: apstools
Requires-Dist: imageio
Requires-Dist: h5py
